setup.py
Wix/guide.py
Wix/main.py
wixcf.egg-info/PKG-INFO
wixcf.egg-info/SOURCES.txt
wixcf.egg-info/dependency_links.txt
wixcf.egg-info/entry_points.txt
wixcf.egg-info/requires.txt
wixcf.egg-info/top_level.txt