Metadata-Version: 1.0
Name: wixcf
Version: 5.2.1
Summary: Wix Package
Home-page: UNKNOWN
Author: Aras Tokdemir
Author-email: aras.tokdemir@outlook.com
License: UNKNOWN
Platform: UNKNOWN
